[
	{
		"asel": false,
		"atype": true,
		"baseAddress": "0x0000000045D10100",
		"channelCount": 1,
		"cslBase": "CSL_QOS_PULSAR_SL_MCU_0_MEMBDG_RMST0_MMR_BASE",
		"deviceName": "PULSAR_SL_MCU_0",
		"epriority": true,
		"name": "MEMBDG_RMST0",
		"orderId": true,
		"qos": true,
		"virtId": true
	},
	{
		"asel": false,
		"atype": true,
		"baseAddress": "0x0000000045D10500",
		"channelCount": 1,
		"cslBase": "CSL_QOS_PULSAR_SL_MCU_0_MEMBDG_WMST0_MMR_BASE",
		"deviceName": "PULSAR_SL_MCU_0",
		"epriority": true,
		"name": "MEMBDG_WMST0",
		"orderId": true,
		"qos": true,
		"virtId": true
	},
	{
		"asel": false,
		"atype": false,
		"baseAddress": "0x0000000045D10900",
		"channelCount": 1,
		"cslBase": "CSL_QOS_PULSAR_SL_MCU_0_CPU0_PMST_MMR_BASE",
		"deviceName": "PULSAR_SL_MCU_0",
		"epriority": true,
		"name": "CPU0_PMST",
		"orderId": true,
		"qos": true,
		"virtId": false
	},
	{
		"asel": false,
		"atype": true,
		"baseAddress": "0x0000000045D11100",
		"channelCount": 1,
		"cslBase": "CSL_QOS_PULSAR_SL_MCU_0_MEMBDG_RMST1_MMR_BASE",
		"deviceName": "PULSAR_SL_MCU_0",
		"epriority": true,
		"name": "MEMBDG_RMST1",
		"orderId": true,
		"qos": true,
		"virtId": true
	},
	{
		"asel": false,
		"atype": true,
		"baseAddress": "0x0000000045D11500",
		"channelCount": 1,
		"cslBase": "CSL_QOS_PULSAR_SL_MCU_0_MEMBDG_WMST1_MMR_BASE",
		"deviceName": "PULSAR_SL_MCU_0",
		"epriority": true,
		"name": "MEMBDG_WMST1",
		"orderId": true,
		"qos": true,
		"virtId": true
	},
	{
		"asel": false,
		"atype": false,
		"baseAddress": "0x0000000045D11900",
		"channelCount": 1,
		"cslBase": "CSL_QOS_PULSAR_SL_MCU_0_CPU1_PMST_MMR_BASE",
		"deviceName": "PULSAR_SL_MCU_0",
		"epriority": true,
		"name": "CPU1_PMST",
		"orderId": true,
		"qos": true,
		"virtId": false
	},
	{
		"asel": false,
		"atype": false,
		"baseAddress": "0x0000000045D13100",
		"channelCount": 1,
		"cslBase": "CSL_QOS_SA2_UL_MCU_0_CTXCACH_EXT_DMA_MMR_BASE",
		"deviceName": "SA2_UL_MCU_0",
		"epriority": true,
		"name": "CTXCACH_EXT_DMA",
		"orderId": true,
		"qos": true,
		"virtId": false
	},
	{
		"asel": false,
		"atype": true,
		"baseAddress": "0x0000000045D20100",
		"channelCount": 1,
		"cslBase": "CSL_QOS_NAVSS_MCU_J7_MCU_0_PROXY0_DST_MMR_BASE",
		"deviceName": "NAVSS_MCU_J7_MCU_0",
		"epriority": true,
		"name": "PROXY0_DST",
		"orderId": true,
		"qos": true,
		"virtId": false
	},
	{
		"asel": false,
		"atype": true,
		"baseAddress": "0x0000000045D20500",
		"channelCount": 1,
		"cslBase": "CSL_QOS_NAVSS_MCU_J7_MCU_0_SEC_PROXY0_DST_MMR_BASE",
		"deviceName": "NAVSS_MCU_J7_MCU_0",
		"epriority": true,
		"name": "SEC_PROXY0_DST",
		"orderId": false,
		"qos": true,
		"virtId": false
	},
	{
		"asel": false,
		"atype": true,
		"baseAddress": "0x0000000045D20D00",
		"channelCount": 1,
		"cslBase": "CSL_QOS_NAVSS_MCU_J7_MCU_0_RINGACC0_DST_MMR_BASE",
		"deviceName": "NAVSS_MCU_J7_MCU_0",
		"epriority": false,
		"name": "RINGACC0_DST",
		"orderId": false,
		"qos": false,
		"virtId": false
	},
	{
		"asel": false,
		"atype": true,
		"baseAddress": "0x0000000045D40100",
		"channelCount": 1,
		"cslBase": "CSL_QOS_NAVSS512L_MAIN_0_PROXY0_DST_MMR_BASE",
		"deviceName": "NAVSS512L_MAIN_0",
		"epriority": true,
		"name": "PROXY0_DST",
		"orderId": true,
		"qos": true,
		"virtId": false
	},
	{
		"asel": false,
		"atype": true,
		"baseAddress": "0x0000000045D40500",
		"channelCount": 1,
		"cslBase": "CSL_QOS_NAVSS512L_MAIN_0_SEC_PROXY0_DST_MMR_BASE",
		"deviceName": "NAVSS512L_MAIN_0",
		"epriority": true,
		"name": "SEC_PROXY0_DST",
		"orderId": false,
		"qos": true,
		"virtId": false
	},
	{
		"asel": false,
		"atype": true,
		"baseAddress": "0x0000000045D48100",
		"channelCount": 1,
		"cslBase": "CSL_QOS_NAVSS512L_MAIN_0_RINGACC0_DST_MMR_BASE",
		"deviceName": "NAVSS512L_MAIN_0",
		"epriority": false,
		"name": "RINGACC0_DST",
		"orderId": false,
		"qos": false,
		"virtId": false
	},
	{
		"asel": false,
		"atype": false,
		"baseAddress": "0x0000000045D50100",
		"channelCount": 1,
		"cslBase": "CSL_QOS_NAVSS512L_MAIN_0_TCU_MSTR_MMR_BASE",
		"deviceName": "NAVSS512L_MAIN_0",
		"epriority": true,
		"name": "TCU_MSTR",
		"orderId": true,
		"qos": true,
		"virtId": false
	},
	{
		"asel": false,
		"atype": false,
		"baseAddress": "0x0000000045D50500",
		"channelCount": 1,
		"cslBase": "CSL_QOS_NAVSS512L_MAIN_0_TCU_MSTW_MMR_BASE",
		"deviceName": "NAVSS512L_MAIN_0",
		"epriority": true,
		"name": "TCU_MSTW",
		"orderId": true,
		"qos": true,
		"virtId": false
	},
	{
		"asel": false,
		"atype": false,
		"baseAddress": "0x0000000045D80100",
		"channelCount": 10,
		"cslBase": "CSL_QOS_ICSS_G_16FFC_MAIN_0_PR1_EXT_VBUSM_MMR_BASE",
		"deviceName": "ICSS_G_16FFC_MAIN_0",
		"epriority": true,
		"name": "PR1_EXT_VBUSM",
		"orderId": true,
		"qos": false,
		"virtId": false
	},
	{
		"asel": false,
		"atype": false,
		"baseAddress": "0x0000000045D80500",
		"channelCount": 10,
		"cslBase": "CSL_QOS_ICSS_G_16FFC_MAIN_1_PR1_EXT_VBUSM_MMR_BASE",
		"deviceName": "ICSS_G_16FFC_MAIN_1",
		"epriority": true,
		"name": "PR1_EXT_VBUSM",
		"orderId": true,
		"qos": false,
		"virtId": false
	},
	{
		"asel": false,
		"atype": true,
		"baseAddress": "0x0000000045D81100",
		"channelCount": 1,
		"cslBase": "CSL_QOS_K3_C66_COREPAC_MAIN_0_C66_MDMA_MMR_BASE",
		"deviceName": "K3_C66_COREPAC_MAIN_0",
		"epriority": true,
		"name": "C66_MDMA",
		"orderId": true,
		"qos": true,
		"virtId": true
	},
	{
		"asel": false,
		"atype": true,
		"baseAddress": "0x0000000045D81500",
		"channelCount": 1,
		"cslBase": "CSL_QOS_K3_C66_COREPAC_MAIN_1_C66_MDMA_MMR_BASE",
		"deviceName": "K3_C66_COREPAC_MAIN_1",
		"epriority": true,
		"name": "C66_MDMA",
		"orderId": true,
		"qos": true,
		"virtId": true
	},
	{
		"asel": false,
		"atype": true,
		"baseAddress": "0x0000000045D82100",
		"channelCount": 1,
		"cslBase": "CSL_QOS_EMMCSD4SS_MAIN_0_EMMCSDSS_RD_MMR_BASE",
		"deviceName": "EMMCSD4SS_MAIN_0",
		"epriority": true,
		"name": "EMMCSDSS_RD",
		"orderId": true,
		"qos": true,
		"virtId": true
	},
	{
		"asel": false,
		"atype": true,
		"baseAddress": "0x0000000045D82500",
		"channelCount": 1,
		"cslBase": "CSL_QOS_EMMCSD4SS_MAIN_0_EMMCSDSS_WR_MMR_BASE",
		"deviceName": "EMMCSD4SS_MAIN_0",
		"epriority": true,
		"name": "EMMCSDSS_WR",
		"orderId": true,
		"qos": true,
		"virtId": true
	},
	{
		"asel": false,
		"atype": true,
		"baseAddress": "0x0000000045D82900",
		"channelCount": 1,
		"cslBase": "CSL_QOS_EMMCSD4SS_MAIN_1_EMMCSDSS_RD_MMR_BASE",
		"deviceName": "EMMCSD4SS_MAIN_1",
		"epriority": true,
		"name": "EMMCSDSS_RD",
		"orderId": true,
		"qos": true,
		"virtId": true
	},
	{
		"asel": false,
		"atype": true,
		"baseAddress": "0x0000000045D82D00",
		"channelCount": 1,
		"cslBase": "CSL_QOS_EMMCSD4SS_MAIN_1_EMMCSDSS_WR_MMR_BASE",
		"deviceName": "EMMCSD4SS_MAIN_1",
		"epriority": true,
		"name": "EMMCSDSS_WR",
		"orderId": true,
		"qos": true,
		"virtId": true
	},
	{
		"asel": false,
		"atype": true,
		"baseAddress": "0x0000000045D84100",
		"channelCount": 1,
		"cslBase": "CSL_QOS_PULSAR_SL_MAIN_0_MEMBDG_RMST0_MMR_BASE",
		"deviceName": "PULSAR_SL_MAIN_0",
		"epriority": true,
		"name": "MEMBDG_RMST0",
		"orderId": true,
		"qos": true,
		"virtId": true
	},
	{
		"asel": false,
		"atype": true,
		"baseAddress": "0x0000000045D84500",
		"channelCount": 1,
		"cslBase": "CSL_QOS_PULSAR_SL_MAIN_0_MEMBDG_RMST1_MMR_BASE",
		"deviceName": "PULSAR_SL_MAIN_0",
		"epriority": true,
		"name": "MEMBDG_RMST1",
		"orderId": true,
		"qos": true,
		"virtId": true
	},
	{
		"asel": false,
		"atype": true,
		"baseAddress": "0x0000000045D84900",
		"channelCount": 1,
		"cslBase": "CSL_QOS_PULSAR_SL_MAIN_0_MEMBDG_WMST0_MMR_BASE",
		"deviceName": "PULSAR_SL_MAIN_0",
		"epriority": true,
		"name": "MEMBDG_WMST0",
		"orderId": true,
		"qos": true,
		"virtId": true
	},
	{
		"asel": false,
		"atype": true,
		"baseAddress": "0x0000000045D84D00",
		"channelCount": 1,
		"cslBase": "CSL_QOS_PULSAR_SL_MAIN_0_MEMBDG_WMST1_MMR_BASE",
		"deviceName": "PULSAR_SL_MAIN_0",
		"epriority": true,
		"name": "MEMBDG_WMST1",
		"orderId": true,
		"qos": true,
		"virtId": true
	},
	{
		"asel": false,
		"atype": true,
		"baseAddress": "0x0000000045D85100",
		"channelCount": 1,
		"cslBase": "CSL_QOS_PULSAR_SL_MAIN_1_MEMBDG_RMST0_MMR_BASE",
		"deviceName": "PULSAR_SL_MAIN_1",
		"epriority": true,
		"name": "MEMBDG_RMST0",
		"orderId": true,
		"qos": true,
		"virtId": true
	},
	{
		"asel": false,
		"atype": true,
		"baseAddress": "0x0000000045D85500",
		"channelCount": 1,
		"cslBase": "CSL_QOS_PULSAR_SL_MAIN_1_MEMBDG_RMST1_MMR_BASE",
		"deviceName": "PULSAR_SL_MAIN_1",
		"epriority": true,
		"name": "MEMBDG_RMST1",
		"orderId": true,
		"qos": true,
		"virtId": true
	},
	{
		"asel": false,
		"atype": true,
		"baseAddress": "0x0000000045D85900",
		"channelCount": 1,
		"cslBase": "CSL_QOS_PULSAR_SL_MAIN_1_MEMBDG_WMST0_MMR_BASE",
		"deviceName": "PULSAR_SL_MAIN_1",
		"epriority": true,
		"name": "MEMBDG_WMST0",
		"orderId": true,
		"qos": true,
		"virtId": true
	},
	{
		"asel": false,
		"atype": true,
		"baseAddress": "0x0000000045D85D00",
		"channelCount": 1,
		"cslBase": "CSL_QOS_PULSAR_SL_MAIN_1_MEMBDG_WMST1_MMR_BASE",
		"deviceName": "PULSAR_SL_MAIN_1",
		"epriority": true,
		"name": "MEMBDG_WMST1",
		"orderId": true,
		"qos": true,
		"virtId": true
	},
	{
		"asel": false,
		"atype": false,
		"baseAddress": "0x0000000045D86100",
		"channelCount": 1,
		"cslBase": "CSL_QOS_COMPUTE_CLUSTER_J7ES_TB_VDC_MAIN_0_GIC_MEM_RD_VBUSM_MMR_BASE",
		"deviceName": "COMPUTE_CLUSTER_J7ES_TB_VDC_MAIN_0",
		"epriority": true,
		"name": "GIC_MEM_RD_VBUSM",
		"orderId": true,
		"qos": true,
		"virtId": false
	},
	{
		"asel": false,
		"atype": false,
		"baseAddress": "0x0000000045D86500",
		"channelCount": 1,
		"cslBase": "CSL_QOS_COMPUTE_CLUSTER_J7ES_TB_VDC_MAIN_0_GIC_MEM_WR_VBUSM_MMR_BASE",
		"deviceName": "COMPUTE_CLUSTER_J7ES_TB_VDC_MAIN_0",
		"epriority": true,
		"name": "GIC_MEM_WR_VBUSM",
		"orderId": true,
		"qos": true,
		"virtId": false
	},
	{
		"asel": false,
		"atype": true,
		"baseAddress": "0x0000000045D87100",
		"channelCount": 1,
		"cslBase": "CSL_QOS_K3_C66_COREPAC_MAIN_0_C66_CFG_MMR_BASE",
		"deviceName": "K3_C66_COREPAC_MAIN_0",
		"epriority": true,
		"name": "C66_CFG",
		"orderId": true,
		"qos": true,
		"virtId": true
	},
	{
		"asel": false,
		"atype": true,
		"baseAddress": "0x0000000045D87500",
		"channelCount": 1,
		"cslBase": "CSL_QOS_K3_C66_COREPAC_MAIN_1_C66_CFG_MMR_BASE",
		"deviceName": "K3_C66_COREPAC_MAIN_1",
		"epriority": true,
		"name": "C66_CFG",
		"orderId": true,
		"qos": true,
		"virtId": true
	},
	{
		"asel": false,
		"atype": true,
		"baseAddress": "0x0000000045D88900",
		"channelCount": 1,
		"cslBase": "CSL_QOS_SA2_UL_MAIN_0_CTXCACH_EXT_DMA_MMR_BASE",
		"deviceName": "SA2_UL_MAIN_0",
		"epriority": true,
		"name": "CTXCACH_EXT_DMA",
		"orderId": true,
		"qos": true,
		"virtId": true
	},
	{
		"asel": false,
		"atype": true,
		"baseAddress": "0x0000000045D89900",
		"channelCount": 1,
		"cslBase": "CSL_QOS_PULSAR_SL_MAIN_0_PBDG_RMST0_MMR_BASE",
		"deviceName": "PULSAR_SL_MAIN_0",
		"epriority": true,
		"name": "PBDG_RMST0",
		"orderId": true,
		"qos": true,
		"virtId": true
	},
	{
		"asel": false,
		"atype": true,
		"baseAddress": "0x0000000045D89D00",
		"channelCount": 1,
		"cslBase": "CSL_QOS_PULSAR_SL_MAIN_0_PBDG_RMST1_MMR_BASE",
		"deviceName": "PULSAR_SL_MAIN_0",
		"epriority": true,
		"name": "PBDG_RMST1",
		"orderId": true,
		"qos": true,
		"virtId": true
	},
	{
		"asel": false,
		"atype": true,
		"baseAddress": "0x0000000045D8A100",
		"channelCount": 1,
		"cslBase": "CSL_QOS_PULSAR_SL_MAIN_0_PBDG_WMST0_MMR_BASE",
		"deviceName": "PULSAR_SL_MAIN_0",
		"epriority": true,
		"name": "PBDG_WMST0",
		"orderId": true,
		"qos": true,
		"virtId": true
	},
	{
		"asel": false,
		"atype": true,
		"baseAddress": "0x0000000045D8A500",
		"channelCount": 1,
		"cslBase": "CSL_QOS_PULSAR_SL_MAIN_0_PBDG_WMST1_MMR_BASE",
		"deviceName": "PULSAR_SL_MAIN_0",
		"epriority": true,
		"name": "PBDG_WMST1",
		"orderId": true,
		"qos": true,
		"virtId": true
	},
	{
		"asel": false,
		"atype": true,
		"baseAddress": "0x0000000045D8A900",
		"channelCount": 1,
		"cslBase": "CSL_QOS_PULSAR_SL_MAIN_1_PBDG_RMST0_MMR_BASE",
		"deviceName": "PULSAR_SL_MAIN_1",
		"epriority": true,
		"name": "PBDG_RMST0",
		"orderId": true,
		"qos": true,
		"virtId": true
	},
	{
		"asel": false,
		"atype": true,
		"baseAddress": "0x0000000045D8AD00",
		"channelCount": 1,
		"cslBase": "CSL_QOS_PULSAR_SL_MAIN_1_PBDG_RMST1_MMR_BASE",
		"deviceName": "PULSAR_SL_MAIN_1",
		"epriority": true,
		"name": "PBDG_RMST1",
		"orderId": true,
		"qos": true,
		"virtId": true
	},
	{
		"asel": false,
		"atype": true,
		"baseAddress": "0x0000000045D8B100",
		"channelCount": 1,
		"cslBase": "CSL_QOS_PULSAR_SL_MAIN_1_PBDG_WMST0_MMR_BASE",
		"deviceName": "PULSAR_SL_MAIN_1",
		"epriority": true,
		"name": "PBDG_WMST0",
		"orderId": true,
		"qos": true,
		"virtId": true
	},
	{
		"asel": false,
		"atype": true,
		"baseAddress": "0x0000000045D8B500",
		"channelCount": 1,
		"cslBase": "CSL_QOS_PULSAR_SL_MAIN_1_PBDG_WMST1_MMR_BASE",
		"deviceName": "PULSAR_SL_MAIN_1",
		"epriority": true,
		"name": "PBDG_WMST1",
		"orderId": true,
		"qos": true,
		"virtId": true
	},
	{
		"asel": false,
		"atype": true,
		"baseAddress": "0x0000000045D8C100",
		"channelCount": 1,
		"cslBase": "CSL_QOS_VPFE_MAIN_0_VBUSM_DMA_MMR_BASE",
		"deviceName": "VPFE_MAIN_0",
		"epriority": true,
		"name": "VBUSM_DMA",
		"orderId": true,
		"qos": true,
		"virtId": true
	},
	{
		"asel": false,
		"atype": false,
		"baseAddress": "0x0000000045D90100",
		"channelCount": 4,
		"cslBase": "CSL_QOS_PCIE_G4X2_MAIN_0_PCIE_MST_RD_HP_MMR_BASE",
		"deviceName": "PCIE_G4X2_MAIN_0",
		"epriority": true,
		"name": "PCIE_MST_RD_HP",
		"orderId": true,
		"qos": true,
		"virtId": false
	},
	{
		"asel": false,
		"atype": false,
		"baseAddress": "0x0000000045D90500",
		"channelCount": 4,
		"cslBase": "CSL_QOS_PCIE_G4X2_MAIN_0_PCIE_MST_RD_LP_MMR_BASE",
		"deviceName": "PCIE_G4X2_MAIN_0",
		"epriority": true,
		"name": "PCIE_MST_RD_LP",
		"orderId": true,
		"qos": true,
		"virtId": false
	},
	{
		"asel": false,
		"atype": false,
		"baseAddress": "0x0000000045D90900",
		"channelCount": 4,
		"cslBase": "CSL_QOS_PCIE_G4X2_MAIN_0_PCIE_MST_WR_HP_MMR_BASE",
		"deviceName": "PCIE_G4X2_MAIN_0",
		"epriority": true,
		"name": "PCIE_MST_WR_HP",
		"orderId": true,
		"qos": true,
		"virtId": false
	},
	{
		"asel": false,
		"atype": false,
		"baseAddress": "0x0000000045D90D00",
		"channelCount": 4,
		"cslBase": "CSL_QOS_PCIE_G4X2_MAIN_0_PCIE_MST_WR_LP_MMR_BASE",
		"deviceName": "PCIE_G4X2_MAIN_0",
		"epriority": true,
		"name": "PCIE_MST_WR_LP",
		"orderId": true,
		"qos": true,
		"virtId": false
	},
	{
		"asel": false,
		"atype": false,
		"baseAddress": "0x0000000045D91100",
		"channelCount": 4,
		"cslBase": "CSL_QOS_PCIE_G4X2_MAIN_1_PCIE_MST_RD_HP_MMR_BASE",
		"deviceName": "PCIE_G4X2_MAIN_1",
		"epriority": true,
		"name": "PCIE_MST_RD_HP",
		"orderId": true,
		"qos": true,
		"virtId": false
	},
	{
		"asel": false,
		"atype": false,
		"baseAddress": "0x0000000045D91500",
		"channelCount": 4,
		"cslBase": "CSL_QOS_PCIE_G4X2_MAIN_1_PCIE_MST_RD_LP_MMR_BASE",
		"deviceName": "PCIE_G4X2_MAIN_1",
		"epriority": true,
		"name": "PCIE_MST_RD_LP",
		"orderId": true,
		"qos": true,
		"virtId": false
	},
	{
		"asel": false,
		"atype": false,
		"baseAddress": "0x0000000045D91900",
		"channelCount": 4,
		"cslBase": "CSL_QOS_PCIE_G4X2_MAIN_1_PCIE_MST_WR_HP_MMR_BASE",
		"deviceName": "PCIE_G4X2_MAIN_1",
		"epriority": true,
		"name": "PCIE_MST_WR_HP",
		"orderId": true,
		"qos": true,
		"virtId": false
	},
	{
		"asel": false,
		"atype": false,
		"baseAddress": "0x0000000045D91D00",
		"channelCount": 4,
		"cslBase": "CSL_QOS_PCIE_G4X2_MAIN_1_PCIE_MST_WR_LP_MMR_BASE",
		"deviceName": "PCIE_G4X2_MAIN_1",
		"epriority": true,
		"name": "PCIE_MST_WR_LP",
		"orderId": true,
		"qos": true,
		"virtId": false
	},
	{
		"asel": false,
		"atype": false,
		"baseAddress": "0x0000000045D92100",
		"channelCount": 4,
		"cslBase": "CSL_QOS_PCIE_G4X2_MAIN_2_PCIE_MST_RD_HP_MMR_BASE",
		"deviceName": "PCIE_G4X2_MAIN_2",
		"epriority": true,
		"name": "PCIE_MST_RD_HP",
		"orderId": true,
		"qos": true,
		"virtId": false
	},
	{
		"asel": false,
		"atype": false,
		"baseAddress": "0x0000000045D92500",
		"channelCount": 4,
		"cslBase": "CSL_QOS_PCIE_G4X2_MAIN_2_PCIE_MST_RD_LP_MMR_BASE",
		"deviceName": "PCIE_G4X2_MAIN_2",
		"epriority": true,
		"name": "PCIE_MST_RD_LP",
		"orderId": true,
		"qos": true,
		"virtId": false
	},
	{
		"asel": false,
		"atype": false,
		"baseAddress": "0x0000000045D92900",
		"channelCount": 4,
		"cslBase": "CSL_QOS_PCIE_G4X2_MAIN_2_PCIE_MST_WR_HP_MMR_BASE",
		"deviceName": "PCIE_G4X2_MAIN_2",
		"epriority": true,
		"name": "PCIE_MST_WR_HP",
		"orderId": true,
		"qos": true,
		"virtId": false
	},
	{
		"asel": false,
		"atype": false,
		"baseAddress": "0x0000000045D92D00",
		"channelCount": 4,
		"cslBase": "CSL_QOS_PCIE_G4X2_MAIN_2_PCIE_MST_WR_LP_MMR_BASE",
		"deviceName": "PCIE_G4X2_MAIN_2",
		"epriority": true,
		"name": "PCIE_MST_WR_LP",
		"orderId": true,
		"qos": true,
		"virtId": false
	},
	{
		"asel": false,
		"atype": false,
		"baseAddress": "0x0000000045D93100",
		"channelCount": 4,
		"cslBase": "CSL_QOS_PCIE_G4X2_MAIN_3_PCIE_MST_RD_HP_MMR_BASE",
		"deviceName": "PCIE_G4X2_MAIN_3",
		"epriority": true,
		"name": "PCIE_MST_RD_HP",
		"orderId": true,
		"qos": true,
		"virtId": false
	},
	{
		"asel": false,
		"atype": false,
		"baseAddress": "0x0000000045D93500",
		"channelCount": 4,
		"cslBase": "CSL_QOS_PCIE_G4X2_MAIN_3_PCIE_MST_RD_LP_MMR_BASE",
		"deviceName": "PCIE_G4X2_MAIN_3",
		"epriority": true,
		"name": "PCIE_MST_RD_LP",
		"orderId": true,
		"qos": true,
		"virtId": false
	},
	{
		"asel": false,
		"atype": false,
		"baseAddress": "0x0000000045D93900",
		"channelCount": 4,
		"cslBase": "CSL_QOS_PCIE_G4X2_MAIN_3_PCIE_MST_WR_HP_MMR_BASE",
		"deviceName": "PCIE_G4X2_MAIN_3",
		"epriority": true,
		"name": "PCIE_MST_WR_HP",
		"orderId": true,
		"qos": true,
		"virtId": false
	},
	{
		"asel": false,
		"atype": false,
		"baseAddress": "0x0000000045D93D00",
		"channelCount": 4,
		"cslBase": "CSL_QOS_PCIE_G4X2_MAIN_3_PCIE_MST_WR_LP_MMR_BASE",
		"deviceName": "PCIE_G4X2_MAIN_3",
		"epriority": true,
		"name": "PCIE_MST_WR_LP",
		"orderId": true,
		"qos": true,
		"virtId": false
	},
	{
		"asel": false,
		"atype": true,
		"baseAddress": "0x0000000045D98100",
		"channelCount": 8,
		"cslBase": "CSL_QOS_USB3P0SS_16FFC_MAIN_0_MSTR0_MMR_BASE",
		"deviceName": "USB3P0SS_16FFC_MAIN_0",
		"epriority": true,
		"name": "MSTR0",
		"orderId": true,
		"qos": true,
		"virtId": true
	},
	{
		"asel": false,
		"atype": true,
		"baseAddress": "0x0000000045D98500",
		"channelCount": 8,
		"cslBase": "CSL_QOS_USB3P0SS_16FFC_MAIN_0_MSTW0_MMR_BASE",
		"deviceName": "USB3P0SS_16FFC_MAIN_0",
		"epriority": true,
		"name": "MSTW0",
		"orderId": true,
		"qos": true,
		"virtId": true
	},
	{
		"asel": false,
		"atype": true,
		"baseAddress": "0x0000000045D98900",
		"channelCount": 8,
		"cslBase": "CSL_QOS_USB3P0SS_16FFC_MAIN_1_MSTR0_MMR_BASE",
		"deviceName": "USB3P0SS_16FFC_MAIN_1",
		"epriority": true,
		"name": "MSTR0",
		"orderId": true,
		"qos": true,
		"virtId": true
	},
	{
		"asel": false,
		"atype": true,
		"baseAddress": "0x0000000045D98D00",
		"channelCount": 8,
		"cslBase": "CSL_QOS_USB3P0SS_16FFC_MAIN_1_MSTW0_MMR_BASE",
		"deviceName": "USB3P0SS_16FFC_MAIN_1",
		"epriority": true,
		"name": "MSTW0",
		"orderId": true,
		"qos": true,
		"virtId": true
	},
	{
		"asel": false,
		"atype": true,
		"baseAddress": "0x0000000045D99D00",
		"channelCount": 1,
		"cslBase": "CSL_QOS_MLBSS2P0_MAIN_0_MLBSS_DMA_VBUSP_MMR_BASE",
		"deviceName": "MLBSS2P0_MAIN_0",
		"epriority": false,
		"name": "MLBSS_DMA_VBUSP",
		"orderId": true,
		"qos": true,
		"virtId": true
	},
	{
		"asel": false,
		"atype": true,
		"baseAddress": "0x0000000045D9A100",
		"channelCount": 1,
		"cslBase": "CSL_QOS_EMMC8SS_16FFC_MAIN_0_EMMCSS_RD_MMR_BASE",
		"deviceName": "EMMC8SS_16FFC_MAIN_0",
		"epriority": true,
		"name": "EMMCSS_RD",
		"orderId": true,
		"qos": true,
		"virtId": true
	},
	{
		"asel": false,
		"atype": true,
		"baseAddress": "0x0000000045D9A500",
		"channelCount": 1,
		"cslBase": "CSL_QOS_EMMC8SS_16FFC_MAIN_0_EMMCSS_WR_MMR_BASE",
		"deviceName": "EMMC8SS_16FFC_MAIN_0",
		"epriority": true,
		"name": "EMMCSS_WR",
		"orderId": true,
		"qos": true,
		"virtId": true
	},
	{
		"asel": false,
		"atype": true,
		"baseAddress": "0x0000000045D9B100",
		"channelCount": 2,
		"cslBase": "CSL_QOS_UFSHCI2P1SS_16FFC_MAIN_0_UFSHCI_VBM_MST_RD_MMR_BASE",
		"deviceName": "UFSHCI2P1SS_16FFC_MAIN_0",
		"epriority": true,
		"name": "UFSHCI_VBM_MST_RD",
		"orderId": true,
		"qos": true,
		"virtId": true
	},
	{
		"asel": false,
		"atype": true,
		"baseAddress": "0x0000000045D9B500",
		"channelCount": 4,
		"cslBase": "CSL_QOS_UFSHCI2P1SS_16FFC_MAIN_0_UFSHCI_VBM_MST_WR_MMR_BASE",
		"deviceName": "UFSHCI2P1SS_16FFC_MAIN_0",
		"epriority": true,
		"name": "UFSHCI_VBM_MST_WR",
		"orderId": true,
		"qos": true,
		"virtId": true
	},
	{
		"asel": false,
		"atype": false,
		"baseAddress": "0x0000000045DA0100",
		"channelCount": 1,
		"cslBase": "CSL_QOS_DEBUGSS_K3_WRAP_CV0_MAIN_0_VBUSMR_MMR_BASE",
		"deviceName": "DEBUGSS_K3_WRAP_CV0_MAIN_0",
		"epriority": true,
		"name": "VBUSMR",
		"orderId": true,
		"qos": true,
		"virtId": false
	},
	{
		"asel": false,
		"atype": false,
		"baseAddress": "0x0000000045DA0500",
		"channelCount": 1,
		"cslBase": "CSL_QOS_DEBUGSS_K3_WRAP_CV0_MAIN_0_VBUSMW_MMR_BASE",
		"deviceName": "DEBUGSS_K3_WRAP_CV0_MAIN_0",
		"epriority": true,
		"name": "VBUSMW",
		"orderId": true,
		"qos": true,
		"virtId": false
	},
	{
		"asel": false,
		"atype": true,
		"baseAddress": "0x0000000045DA4100",
		"channelCount": 1,
		"cslBase": "CSL_QOS_PULSAR_SL_MAIN_0_CPU0_PMST_MMR_BASE",
		"deviceName": "PULSAR_SL_MAIN_0",
		"epriority": true,
		"name": "CPU0_PMST",
		"orderId": true,
		"qos": true,
		"virtId": true
	},
	{
		"asel": false,
		"atype": true,
		"baseAddress": "0x0000000045DA4500",
		"channelCount": 1,
		"cslBase": "CSL_QOS_PULSAR_SL_MAIN_0_CPU1_PMST_MMR_BASE",
		"deviceName": "PULSAR_SL_MAIN_0",
		"epriority": true,
		"name": "CPU1_PMST",
		"orderId": true,
		"qos": true,
		"virtId": true
	},
	{
		"asel": false,
		"atype": true,
		"baseAddress": "0x0000000045DA4900",
		"channelCount": 1,
		"cslBase": "CSL_QOS_PULSAR_SL_MAIN_1_CPU0_PMST_MMR_BASE",
		"deviceName": "PULSAR_SL_MAIN_1",
		"epriority": true,
		"name": "CPU0_PMST",
		"orderId": true,
		"qos": true,
		"virtId": true
	},
	{
		"asel": false,
		"atype": true,
		"baseAddress": "0x0000000045DA4D00",
		"channelCount": 1,
		"cslBase": "CSL_QOS_PULSAR_SL_MAIN_1_CPU1_PMST_MMR_BASE",
		"deviceName": "PULSAR_SL_MAIN_1",
		"epriority": true,
		"name": "CPU1_PMST",
		"orderId": true,
		"qos": true,
		"virtId": true
	},
	{
		"asel": false,
		"atype": true,
		"baseAddress": "0x0000000045DC0100",
		"channelCount": 32,
		"cslBase": "CSL_QOS_DMPAC_TOP_MAIN_0_DATA_MST_MMR_BASE",
		"deviceName": "DMPAC_TOP_MAIN_0",
		"epriority": false,
		"name": "DATA_MST",
		"orderId": false,
		"qos": false,
		"virtId": true
	},
	{
		"asel": false,
		"atype": true,
		"baseAddress": "0x0000000045DC0500",
		"channelCount": 2,
		"cslBase": "CSL_QOS_K3_D5520MP2_MAIN_0_M_VBUSM_R_MMR_BASE",
		"deviceName": "K3_D5520MP2_MAIN_0",
		"epriority": true,
		"name": "M_VBUSM_R",
		"orderId": true,
		"qos": true,
		"virtId": true
	},
	{
		"asel": false,
		"atype": true,
		"baseAddress": "0x0000000045DC0900",
		"channelCount": 2,
		"cslBase": "CSL_QOS_K3_D5520MP2_MAIN_0_M_VBUSM_W_MMR_BASE",
		"deviceName": "K3_D5520MP2_MAIN_0",
		"epriority": true,
		"name": "M_VBUSM_W",
		"orderId": true,
		"qos": true,
		"virtId": true
	},
	{
		"asel": false,
		"atype": true,
		"baseAddress": "0x0000000045DC0D00",
		"channelCount": 5,
		"cslBase": "CSL_QOS_K3_VXE384MP2_MAIN_0_M_VBUSM_R_MMR_BASE",
		"deviceName": "K3_VXE384MP2_MAIN_0",
		"epriority": true,
		"name": "M_VBUSM_R",
		"orderId": true,
		"qos": true,
		"virtId": true
	},
	{
		"asel": false,
		"atype": true,
		"baseAddress": "0x0000000045DC1100",
		"channelCount": 5,
		"cslBase": "CSL_QOS_K3_VXE384MP2_MAIN_0_M_VBUSM_W_MMR_BASE",
		"deviceName": "K3_VXE384MP2_MAIN_0",
		"epriority": true,
		"name": "M_VBUSM_W",
		"orderId": true,
		"qos": true,
		"virtId": true
	},
	{
		"asel": false,
		"atype": true,
		"baseAddress": "0x0000000045DC1500",
		"channelCount": 32,
		"cslBase": "CSL_QOS_VPAC_TOP_MAIN_0_DATA_MST_0_MMR_BASE",
		"deviceName": "VPAC_TOP_MAIN_0",
		"epriority": false,
		"name": "DATA_MST_0",
		"orderId": false,
		"qos": false,
		"virtId": true
	},
	{
		"asel": false,
		"atype": true,
		"baseAddress": "0x0000000045DC1900",
		"channelCount": 64,
		"cslBase": "CSL_QOS_VPAC_TOP_MAIN_0_DATA_MST_1_MMR_BASE",
		"deviceName": "VPAC_TOP_MAIN_0",
		"epriority": false,
		"name": "DATA_MST_1",
		"orderId": false,
		"qos": false,
		"virtId": true
	},
	{
		"asel": false,
		"atype": true,
		"baseAddress": "0x0000000045DC1D00",
		"channelCount": 3,
		"cslBase": "CSL_QOS_VPAC_TOP_MAIN_0_LDC0_M_MST_MMR_BASE",
		"deviceName": "VPAC_TOP_MAIN_0",
		"epriority": true,
		"name": "LDC0_M_MST",
		"orderId": true,
		"qos": true,
		"virtId": true
	},
	{
		"asel": false,
		"atype": true,
		"baseAddress": "0x0000000045DC2100",
		"channelCount": 10,
		"cslBase": "CSL_QOS_K3_DSS_MAIN_0_DSS_INST0_VBUSM_DMA_MMR_BASE",
		"deviceName": "K3_DSS_MAIN_0",
		"epriority": false,
		"name": "DSS_INST0_VBUSM_DMA",
		"orderId": true,
		"qos": true,
		"virtId": true
	},
	{
		"asel": false,
		"atype": true,
		"baseAddress": "0x0000000045DC2500",
		"channelCount": 10,
		"cslBase": "CSL_QOS_K3_DSS_MAIN_0_DSS_INST0_VBUSM_FBDC_MMR_BASE",
		"deviceName": "K3_DSS_MAIN_0",
		"epriority": false,
		"name": "DSS_INST0_VBUSM_FBDC",
		"orderId": true,
		"qos": true,
		"virtId": true
	},
	{
		"asel": false,
		"atype": true,
		"baseAddress": "0x0000000045DC5100",
		"channelCount": 48,
		"cslBase": "CSL_QOS_J7_LASCAR_GPU_WRAP_MAIN_0_M0_VBUSM_R_ASYNC_MMR_BASE",
		"deviceName": "J7_LASCAR_GPU_WRAP_MAIN_0",
		"epriority": true,
		"name": "M0_VBUSM_R_ASYNC",
		"orderId": true,
		"qos": true,
		"virtId": true
	},
	{
		"asel": false,
		"atype": true,
		"baseAddress": "0x0000000045DC5900",
		"channelCount": 48,
		"cslBase": "CSL_QOS_J7_LASCAR_GPU_WRAP_MAIN_0_M0_VBUSM_W_ASYNC_MMR_BASE",
		"deviceName": "J7_LASCAR_GPU_WRAP_MAIN_0",
		"epriority": true,
		"name": "M0_VBUSM_W_ASYNC",
		"orderId": true,
		"qos": true,
		"virtId": true
	},
	{
		"asel": false,
		"atype": true,
		"baseAddress": "0x0000000045DC6100",
		"channelCount": 48,
		"cslBase": "CSL_QOS_J7_LASCAR_GPU_WRAP_MAIN_0_M1_VBUSM_R_ASYNC_MMR_BASE",
		"deviceName": "J7_LASCAR_GPU_WRAP_MAIN_0",
		"epriority": true,
		"name": "M1_VBUSM_R_ASYNC",
		"orderId": true,
		"qos": true,
		"virtId": true
	},
	{
		"asel": false,
		"atype": true,
		"baseAddress": "0x0000000045DC6900",
		"channelCount": 48,
		"cslBase": "CSL_QOS_J7_LASCAR_GPU_WRAP_MAIN_0_M1_VBUSM_W_ASYNC_MMR_BASE",
		"deviceName": "J7_LASCAR_GPU_WRAP_MAIN_0",
		"epriority": true,
		"name": "M1_VBUSM_W_ASYNC",
		"orderId": true,
		"qos": true,
		"virtId": true
	}
]
